openesef/__init__.py
openesef/build.py
openesef/version.py
openesef/base/__init__.py
openesef/base/archiver.py
openesef/base/const.py
openesef/base/cube.py
openesef/base/data_wrappers.py
openesef/base/ebase.py
openesef/base/element.py
openesef/base/fbase.py
openesef/base/pool.py
openesef/base/resolver.py
openesef/base/tax_to_pd.py
openesef/base/try_virtualfs.py
openesef/base/util.py
openesef/edgar/__init__.py
openesef/edgar/document.py
openesef/edgar/document_text.py
openesef/edgar/dtd.py
openesef/edgar/edgar.py
openesef/edgar/filing.py
openesef/edgar/financials.py
openesef/edgar/loader.py
openesef/edgar/requests_wrapper.py
openesef/edgar/sgml.py
openesef/edgar/stock.py
openesef/edgar/verpkl.py
openesef/edgar/xbrl_worker.py
openesef/engines/__init__.py
openesef/engines/base_reporter.py
openesef/engines/html_helper.py
openesef/engines/integrator.py
openesef/engines/tax_pres.c
openesef/engines/tax_pres.cpython-311-darwin.so
openesef/engines/tax_pres.pyx
openesef/engines/tax_reporter.py
openesef/engines/tlb_reporter.py
openesef/filings_xbrl_org/__init__.py
openesef/filings_xbrl_org/api.py
openesef/instance/__init__.py
openesef/instance/context.py
openesef/instance/dei.py
openesef/instance/fact.py
openesef/instance/footnote.py
openesef/instance/instance.py
openesef/instance/m_xbrl.py
openesef/instance/unit.py
openesef/ixbrl/__init__.py
openesef/ixbrl/m_format.py
openesef/ixbrl/m_ixbrl.py
openesef/taxonomy/__init__.py
openesef/taxonomy/arc.py
openesef/taxonomy/arcroletype.py
openesef/taxonomy/base_set.py
openesef/taxonomy/concept.py
openesef/taxonomy/item_type.py
openesef/taxonomy/label.py
openesef/taxonomy/linkbase.py
openesef/taxonomy/linkbase_pre.py
openesef/taxonomy/locator.py
openesef/taxonomy/resource.py
openesef/taxonomy/roletype.py
openesef/taxonomy/schema.py
openesef/taxonomy/simple_type.py
openesef/taxonomy/taxonomy.py
openesef/taxonomy/tpack.py
openesef/taxonomy/tuple_type.py
openesef/taxonomy/xlink.py
openesef/taxonomy/formula/__init__.py
openesef-0.3.8.29.dist-info/licenses/LICENSE
openesef-0.3.8.29.dist-info/METADATA
openesef-0.3.8.29.dist-info/WHEEL
openesef-0.3.8.29.dist-info/top_level.txt
openesef-0.3.8.29.dist-info/RECORD
