Metadata-Version: 2.4
Name: openesef
Version: 0.3.8.29
Summary: An open-source Python library for ESEF XBRL filings
Home-page: https://github.com/reeyarn/openesef
Author: Reeyarn Zhiyang Li
Author-email: Reeyarn Zhiyang Li <reeyarn@gmail.com>
License: GPL-3.0
Project-URL: Homepage, https://github.com/reeyarn/openesef
Project-URL: Author, https://reeyarn.li
Classifier: Programming Language :: Python :: 3
Classifier: License :: OSI Approved :: GNU General Public License v3 (GPLv3)
Classifier: Operating System :: OS Independent
Requires-Python: >=3.10
License-File: LICENSE
Requires-Dist: thefuzz>=0.22.1
Requires-Dist: pandas>=2.2.0
Requires-Dist: fs>=2.4.16
Requires-Dist: python-dateutil>=2.9.0
Requires-Dist: requests>=2.32.3
Requires-Dist: beautifulsoup4>=4.13.3
Requires-Dist: lxml>=5.3.0
Requires-Dist: psutil>=5.8.0
Requires-Dist: pyarrow>=19.0.0
Requires-Dist: fastparquet>=2024.11.0
Requires-Dist: numpy>=2.2.0
Requires-Dist: cython>=3.0.0
Requires-Dist: tomli>=2.0.1
Requires-Dist: tqdm>=4.60.0
Requires-Dist: requests>=2.32.0
Dynamic: author
Dynamic: home-page
Dynamic: license-file
